brightwheel_photos/.editorconfig
brightwheel_photos/__init__.py
brightwheel_photos/cli.py
brightwheel_photos-1.0.0.dist-info/METADATA
brightwheel_photos-1.0.0.dist-info/WHEEL
brightwheel_photos-1.0.0.dist-info/entry_points.txt
brightwheel_photos-1.0.0.dist-info/licenses/LICENSE
brightwheel_photos-1.0.0.dist-info/RECORD
