Metadata-Version: 2.4
Name: brightwheel-photos
Version: 1.0.0
Summary: CLI tool for downloading a student's photos from Brightwheel.
Author-email: Johnathan Gilday <me@johnathangilday.com>
License-File: LICENSE
Requires-Python: >=3.8
Requires-Dist: certifi==2023.7.22
Requires-Dist: chardet==4.0.0
Requires-Dist: idna==2.10
Requires-Dist: piexif==1.1.3
Requires-Dist: pillow>=10.1.0
Requires-Dist: plum-py==0.3.1
Requires-Dist: python-dotenv>=1.0.0
Requires-Dist: requests>=2.31.0
Requires-Dist: urllib3==1.26.19
